H2oMojoPredict/__init__.py
H2oMojoPredict/h2o_predict_java8.jar
H2oMojoPredict/test.py
H2oMojoPredict-0.1.3.dist-info/METADATA
H2oMojoPredict-0.1.3.dist-info/WHEEL
H2oMojoPredict-0.1.3.dist-info/top_level.txt
H2oMojoPredict-0.1.3.dist-info/RECORD
