Metadata-Version: 2.1
Name: H2oMojoPredict
Version: 0.1.3
Summary: In H2oMojoPreidct, you can perform predictions on MOJO files without the need for H2O initialization or dependency on an H2O cluster. You are free to use Python to make predictions using MOJO files.
Home-page: https://github.com/lianyukun
Author: yklian
Author-email: 923412504@qq.com
License: MIT
Classifier: Development Status :: 3 - Alpha
Classifier: Intended Audience :: Developers
Classifier: License :: OSI Approved :: MIT License
Classifier: Programming Language :: Python :: 3.7
Requires-Dist: pandas (==1.1.5)
